ship_kit/__init__.py
ship_kit/_modidx.py
ship_kit/admin.py
ship_kit/admin_routes.py
ship_kit/auth.py
ship_kit/permissions.py
ship_kit/routes/__init__.py
ship_kit/routes/auth.py
ship_kit-0.0.5.dist-info/licenses/LICENSE
ship_kit-0.0.5.dist-info/METADATA
ship_kit-0.0.5.dist-info/WHEEL
ship_kit-0.0.5.dist-info/entry_points.txt
ship_kit-0.0.5.dist-info/top_level.txt
ship_kit-0.0.5.dist-info/RECORD
