Metadata-Version: 2.4
Name: ship-kit
Version: 0.0.5
Summary: A FastHTML toolkit for building production-ready SaaS applications with authentication, admin panels, billing, and team management
Home-page: https://github.com/LotsOfOrg/ship-kit
Author: Matthew Redrup
Author-email: 16837301+Matthew-Redrup@users.noreply.github.com
License: Apache Software License 2.0
Keywords: nbdev jupyter notebook python
Classifier: Development Status :: 4 - Beta
Classifier: Intended Audience :: Developers
Classifier: Natural Language :: English
Classifier: Programming Language :: Python :: 3.10
Classifier: Programming Language :: Python :: 3.11
Classifier: Programming Language :: Python :: 3.12
Classifier: License :: OSI Approved :: Apache Software License
Requires-Python: >=3.10
License-File: LICENSE
Requires-Dist: python-fasthtml>=0.12.18
Requires-Dist: monsterui>=1.0.20
Requires-Dist: bcrypt>=4.1.2
Requires-Dist: fastlite>=0.0.16
Provides-Extra: dev
Requires-Dist: nbdev; extra == "dev"
Requires-Dist: jupyterlab; extra == "dev"
Requires-Dist: jupyterlab-quarto; extra == "dev"
Requires-Dist: twine; extra == "dev"
Dynamic: author
Dynamic: author-email
Dynamic: classifier
Dynamic: description
Dynamic: description-content-type
Dynamic: home-page
Dynamic: keywords
Dynamic: license
Dynamic: license-file
Dynamic: provides-extra
Dynamic: requires-dist
Dynamic: requires-python
Dynamic: summary
